{
    "collectionsColumn": "Gyűjtemények",
    "collectionsColumn/collectionError": "Hiba történt a gyűjtemény részleteinek betöltésekor. Kérjük, próbálja meg a fenti frissítést",
    "bookmarksColumn": "Könyvjelzők",
    "searchBar/placeholder": "Keressen modelleket a Hugging Face oldalon...",
    "searchBar/huggingFaceError": "Hiba történt a Hugging Face eredményeinek lekérésekor. Kérjük, próbálja újra egy kis idő múlva",
    "sortBy": "Rendezés",
    "searchSortKey.default/title": "Legjobb meccs",
    "searchSortKey.likes/title": "A legtöbb lájk",
    "searchSortKey.downloads/title": "A legtöbb letöltés",
    "searchSortKey.lastModified/title": "Nemrég frissítve",
    "searchSortKey.createdAt/title": "Nemrég létrehozva",
    "download.option.willFitEstimation.caveat": "Más tényezők is akadályozhatják a betöltését, például a modell architektúrája, a modellfájl integritása vagy a számítógépen rendelkezésre álló memória mennyisége.",
    "download.option.willFitEstimation.fullGPUOffload/title": "Teljes GPU-letöltés lehetséges",
    "download.option.willFitEstimation.fullGPUOffload/description": "Lehet, hogy ez a modell teljesen belefér a GPU memóriájába. Ez jelentősen felgyorsíthatja a következtetést.",
    "download.option.willFitEstimation.partialGPUOffload/title": "Részleges GPU tehermentesítés lehetséges",
    "download.option.willFitEstimation.partialGPUOffload/description": "Ez a modell részben elférhet a GPU memóriájában.  Ez gyakran jelentősen felgyorsíthatja a következtetést.",
    "download.option.willFitEstimation.fitWithoutGPU/title": "Valószínűleg alkalmas",
    "download.option.willFitEstimation.fitWithoutGPU/description": "Ez a modell valószínűleg elfér a gép memóriájában.",
    "download.option.willFitEstimation.willNotFit/title": "Valószínűleg túl nagy ehhez a géphez",
    "download.option.willFitEstimation.willNotFit/description": "A modellfájl sikeres használatához szükséges memóriaigény meghaladhatja a számítógépen rendelkezésre álló erőforrásokat. A fájl letöltése NEM javasolt.",
    "download.option.recommended/title": "Ajánlott",
    "download.option.recommended/description": "A hardvertől függően ez a lehetőség javasolt.",
    "download.option.downloaded/title": "Letöltve",
    "download.option.downloading/title": "Letöltés ({{progress Percentile}}%)",
    "feed.action.refresh": "Hírcsatorna frissítése"
}