{
  "modelLoaderPlaceholder": "选择要加载的模型",
  "systemPromptPlaceholder": "设置系统提示词",
  "userRoleText": "用户",
  "assistantRoleText": "助手",
  "addMessageButtonText": "添加",
  "addMessageButtonText/toolTip": "插入一条消息到上下文中，但不触发预测",
  "sendMessageButtonText": "发送",
  "sendMessageButtonText/toolTip": "将你的提示词和对话历史发送给模型处理",
  "ejectButtonText": "卸载",
  "unloadTooltip": "从内存中卸载模型",
  "cancelButtonText": "取消",
  "loadButtonText": "加载",
  "advancedSegmentText": "高级",
  "chatSegmentText": "对话",
  "chatSidebarTitle": "对话列表",
  "newChatButton": "新建",
  "newFolderButton": "新建文件夹",
  "viewModeLabel": "视图模式",
  "noChatSelected": "未选择对话",
  "chatViewOptions": "对话视图选项",
  "uiControls/title": "显示设置",
  "noChatSelectedPlaceholder": "选择一个对话",
  "unnamedChat": "未命名对话",
  "emptyFolder": "文件夹为空",

  "tokenCount": "Token 数量",
  "messageTokenCount": "输入 Token 数量",
  "tokenCount/hint": "消息中的 Token 数量。使用当前选中模型的分词器统计。\n\n需要模型已加载。",
  "messageTokenCount/hint": "消息中的 Token 数量。使用当前选中模型的分词器统计。\n\n**不包含**文件附件的 Token 估算。",

  "notes": "对话笔记",
  "notes/add/first": "添加笔记",
  "notes/add/another": "添加另一条笔记",
  "notes/hint": "为此对话保存笔记。笔记仅供你参考，不会发送给模型。所有更改自动保存。",
  "notes/placeholder": "在此输入笔记...",
  "notes/delete": "删除笔记",
  "notes/noteLabel": "笔记",
  "notes/copyContent": "复制笔记内容",

  "actions/sendMessage/error": "发送消息失败",
  "actions/loadModel/error": "🥲 加载模型失败",
  "actions/addFile": "[实验性功能] 附加文件到此消息\n(.pdf、纯文本或 .docx)",
  "actions/addFile/label": "附加文件",
  "actions/changeRole": "在用户和助手角色之间切换。\n\n这有助于引导对话朝特定方向发展。\n\n可用于设置\"少样本学习\"或\"上下文学习\"场景",
  "actions/addImage": "附加图片",
  "actions/deleteMessage": "删除消息",
  "actions/deleteMessage/confirmation": "确定要删除此消息吗？",
  "actions/copyMessage": "复制消息",
  "actions/editMessage": "编辑消息",
  "actions/editMessage/cannotEditPreprocessed": "无法编辑预处理后的消息，因为运行预处理器后它们会被覆盖。要编辑消息，请：\n\n - 切换到原始消息并进行编辑，或\n - 修改预处理器以产生期望的输出。",
  "actions/regenerateMessage": "重新生成消息",
  "actions/regenerateMessage/error": "重新生成消息失败",
  "actions/branchChat": "从此消息分支对话",
  "actions/branchChat/error": "分支对话失败",
  "actions/continueAssistantMessage": "继续助手消息",
  "actions/continueAssistantMessage/error": "继续助手消息失败",
  "actions/predictNext": "生成 AI 回复",
  "actions/predictNext/error": "生成 AI 回复失败",
  "actions/loadLastModel": "重新加载上次使用的模型",
  "actions/loadLastModel/tooltip": "点击加载此对话上次使用的模型：\n\n{{lastModel}}",
  "actions/loadLastModel/error": "加载上次使用的模型失败。",
  "actions/clearLastUsedModel": "清除上次使用的模型",
  "actions/clearLastUsedModel/error": "清除上次使用的模型失败。",
  "actions/continueCurrentModel": "使用当前模型",
  "actions/continueCurrentModel/tooltip": "当前模型：{{currentModel}}",
  "actions/changeToLastUsedModel": "加载 {{lastModel}}",
  "actions/changeToLastUsedModel/error": "切换到上次使用的模型失败。",
  "actions/changeToLastUsedModel/tooltip": "你上次在此对话中发送消息时使用了不同的模型。点击卸载当前选中的模型（{{currentModel}}）并加载此对话上次使用的模型：\n\n{{lastModel}}",
  "actions/switchToLastUsedModel": "切换到 {{lastModel}}",
  "actions/switchToLastUsedModel/tooltip": "点击切换到上次使用的模型：\n\n{{lastModel}}",
  "actions/loadModel": "加载模型",
  "actions/toggleViewingProcessed/currentlyFalse": "当前正在查看原始消息。点击查看预处理后的消息。",
  "actions/toggleViewingProcessed/currentlyTrue": "当前正在查看预处理后的消息。点击查看原始消息。",
  "actions/toggleViewingProcessed/hint": "消息发送给模型前，可能会由提示词预处理器进行预处理。点击可在查看原始消息和预处理后消息之间切换。只有预处理后的消息会发送给模型。",
  "editMessageConfirm/title": "保留更改？",
  "editMessageConfirm/message": "你已修改消息。是否保留更改？",
  "editMessageConfirm/keepEditing": "继续编辑",
  "editMessageConfirm/save": "保存",
  "editMessageConfirm/discard": "放弃更改",
  "tokenCount/totalNotAvailable": "Token：{{current}}",
  "tokenCount/totalAvailable": "Token：{{current}}/{{total}}",
  "tokenCount/totalAvailablePercentage": "上下文已使用 {{percentage}}%",
  "tokenCount/contextOverflow": "未处理的上下文超过了模型的最大 Token 限制。根据你的上下文溢出策略，上下文可能会被截断或消息可能无法发送。",
  "modelLoader/manualLoadParams/label": "手动选择模型加载参数",
  "modelLoader/manualLoadParams/hint/before": "（或按住 ",
  "modelLoader/manualLoadParams/hint/after": "）",
  "actions/move/error": "移动失败",
  "actions/rename/error": "重命名失败",
  "actions/createChatAtRoot": "新建对话...",
  "actions/createChatAtRoot/error": "在根目录创建对话失败",
  "actions/createFolderAtRoot": "新建文件夹...",
  "actions/createFolderAtRoot/error": "在根目录创建文件夹失败",
  "actions/openInFolder/mac": "在 Finder 中显示",
  "actions/openInFolder/pc": "在文件资源管理器中显示",

  "actions/createChat/error": "创建对话失败",
  "actions/deleteChat/errorTitle": "删除对话失败",

  "userFile/fileSizeLimit": "文件大小限制为 ",
  "userFile/noImageSupport": "模型不支持图片输入",
  "userFile/errorPrefix": "错误 - ",
  "userFile/supportedImagePrefix": "不支持的图片类型 - 仅支持 ",
  "userFile/supportedImageSuffix": "",
  "userFile/unsupportedFileType": "不支持的文件类型 - 仅支持图片、PDF 和 .txt 文件。",
  "userFile/maxFilesPerMessage": "每条消息的文件数量已达上限。无法添加超过 {{files}} 个文件。",
  "userFile/maxFileSizePerMessage": "每条消息的文件大小已达上限。无法添加超过 {{size}} 的文件。",
  "userFile/maxFileSizePerConversation": "每个对话的文件大小已达上限。无法添加超过 {{size}} 的文件。",
  "userFile/failedToUploadError/title": "上传文件失败",
  "userFile/failedToAddFile/title": "添加文件到对话失败",
  "errorTitle": "错误",
  "userFile/chatTerminalDocumentsCount_one": "对话中有 {{count}} 个文档",
  "userFile/chatTerminalDocumentsCount_other": "对话中有 {{count}} 个文档",

  "prediction/busyModel/title": "模型正忙",
  "prediction/busyModel/message": "请等待模型完成后再试",
  "prediction/noModel/title": "未选择模型",
  "prediction/modelLoading": "消息已排队，将在模型加载完成后发送",
  "prediction/noModel/message": "选择模型以发送消息",
  "prediction/unloadModel/error": "卸载模型失败",

  "retrieval/user/processingLabel": "AI 正在思考...",
  "retrieval/powerUser/intermediateStepsHidden": "中间步骤已隐藏。点击展开。",
  "retrieval/actions/clickToExpand": "点击展开中间步骤",
  "retrieval/actions/clickToCollapse": "点击收起中间步骤",

  "style": "外观",

  "style/viewMode/markdown": "Markdown",
  "style/viewMode/plaintext": "纯文本",
  "style/viewMode/monospace": "等宽字体",

  "speculativeDecodingVisualization/toggle": "可视化已接受的草稿 Token",
  "speculativeDecodingVisualization/fromDraftModel_one": "已接受的草稿 Token",
  "speculativeDecodingVisualization/fromDraftModel_other": "已接受的草稿 Token",
  "speculativeDecodingVisualization/cannotChangeViewMode": "可视化草稿 Token 时无法更改视图模式。",

  "style/fontSize/label": "字体大小",
  "style/fontSize/medium": "默认",
  "style/fontSize/large": "大",
  "style/fontSize/small": "小",

  "style/debugBlocks/label": "显示调试信息块",

  "style/thinkingUI/label": "默认展开推理块",
  "style/chatFullWidth/label": "将对话容器扩展到窗口宽度",

  "style/chatUtilityMenusShowLabel/label": "显示对话工具菜单标签",

  "messageBlocks": {
    "expandBlockTooltip": "展开内容",
    "collapseBlockTooltip": "收起内容",
    "debug": {
      "label": "调试信息",
      "collapseTooltip": "收起调试信息块",
      "expandTooltip": "展开调试信息块"
    }
  },

  "chatTabOptions/clearAllMessages": "清空所有消息...",
  "chatTabOptions/duplicateChat": "复制对话",

  "topBarActions/duplicateChat": "复制",
  "topBarActions/clearChat": "清空全部",
  "topBarActions/clearChatConfirmation": "确定要清空此对话中的所有消息吗？",
  "topBarActions/clearChatCancel": "取消",
  "topBarActions/clearChatDelete": "清空全部",

  "noModels.indexing": "正在索引模型文件...（可能需要片刻）",
  "noModels.downloading": "正在下载你的第一个大语言模型...",
  "noModels": "还没有大语言模型！下载一个开始使用吧！",

  "plugins": {
    "pluginTrigger": {
      "noPlugins": "插件",
      "multiplePlugins": "{{dynamicValue}} 个插件"
    },
    "pluginSelect": {
      "title": "插件",
      "dropdown": {
        "configure": "配置",
        "disable": "禁用",
        "fork": "分叉",
        "uninstall": "卸载"
      },
      "actionButtons": {
        "create": "创建",
        "import": "导入",
        "discover": "发现"
      },
      "recentlyCreated": {
        "title": "最近创建的插件",
        "placeholder": "你创建的插件将显示在此处"
      },
      "startRunningDevelopmentPlugin/error": "启动开发模式插件失败",
      "stopRunningDevelopmentPlugin/error": "停止开发模式插件失败",
      "forceReInitPlugin/error": "重启插件失败"
    },
    "pluginConfiguration": {
      "title": "插件配置",
      "selectAPlugin": "选择插件以编辑其配置",
      "preprocessorAndGenerator": "此插件包含自定义预处理器和生成器",
      "generatorOnly": "此插件包含自定义生成器",
      "preprocessorOnly": "此插件包含自定义预处理器"
    },
    "instructions": {
      "runTheFollowing": "要运行插件，请打开终端并输入",
      "pushTo": "推送到 Hub 与他人分享你的插件（可选）",
      "createdSuccessfully": "插件创建成功",
      "creatingPlugin": "正在创建插件...",
      "projectFilesTitle": "项目文件",
      "buttons": {
        "documentation": "文档",
        "dismiss": "关闭",
        "publish": "发布",
        "openInZed": "在 Zed 中打开",
        "openInVscode": "在 VS Code 中打开",
        "revealInFinder": "在 Finder 中显示",
        "openInFileExplorer": "在文件资源管理器中打开"
      }
    },
    "localFork": {
      "error": "创建插件本地开发副本失败。"
    },
    "restartErrorPlugin/error": "重启插件失败"
  },

  "genInfo": {
    "tokensPerSecond": "{{tokensPerSecond}} Token/秒",
    "predictedTokensCount": "{{predictedTokensCount}} 个 Token",
    "timeToFirstTokenSec": "首 Token 时间 {{timeToFirstTokenSec}} 秒",
    "stopReason": "停止原因：{{stopReason}}",
    "stopReason.userStopped": "用户停止",
    "stopReason.modelUnloaded": "模型已卸载",
    "stopReason.failed": "生成失败",
    "stopReason.eosFound": "找到 EOS Token",
    "stopReason.stopStringFound": "找到停止字符串",
    "stopReason.toolCalls": "工具调用",
    "stopReason.maxPredictedTokensReached": "达到最大预测 Token 数",
    "stopReason.contextLengthReached": "达到上下文长度限制",
    "speculativeDecodedBy": "草稿模型：{{decodedBy}}",
    "speculativeDecodingStats": "已接受 {{accepted}}/{{total}} 个草稿 Token（{{percentage}}%）",
    "speculativeDecodingAcceptedPercentage": "{{percentage}}% 草稿 Token 被接受",
    "speculativeDecodingTooltip": "已接受 {{accepted}}/{{total}} 个草稿 Token"
  },

  "tabs": {
    "systemPromptEditorTab.headerLabel": "编辑系统提示词"
  }
}
