{
  "postDownloadActionExecutor.zipExtraction/status": "Extraction...",
  "finalizing": "Finalisation...",
  "noOptions": "Aucune option compatible disponible pour le téléchargement",
  
  "deeplink/confirmation/title": "Télécharger le modèle depuis Hugging Face 🤗",
  "deeplink/confirmation/subtitle": "{{modelName}}",
  "deeplink/confirmation/selectRecommended": "Sélectionner recommandé",
  "deeplink/confirmation/selectOption": "Sélectionner l'option de téléchargement",
  "deeplink/confirmation/recommendedOption": "Probablement la meilleure option pour la plupart des utilisateurs",
  "deeplink/confirmation/downloadButton": "Télécharger",
  "deeplink/confirmation/nevermindButton": "Peu importe",
  "deeplink/confirmation/modelPresent/title": "Modèle Hugging Face trouvé ✅",
  "deeplink/confirmation/modelPresent/body": "Bonne nouvelle ! Ce fichier modèle est déjà disponible sur votre machine locale.",
  "deeplink/confirmation/loadInChat": "Charger {{modelName}} dans une nouvelle discussion",
  "deeplink/error/modelNotFound/title": "Ruh roh, nous n'avons pas pu trouver ce modèle",
  "deeplink/error/modelNotFound/body": "Vérifiez le nom du modèle et envisagez d'essayer une autre option de téléchargement."
}
