{
    "title": "Geliştirici",
    "subtitle": "Geliştirici araçlarını ve API ayarlarını yapılandırın.",
    "apiSettings": "API Ayarları",
    "serverStatus": "Sunucu Durumu",
    "port": "Port",
    "host": "Host/Sunucu",
    "apiKey": "API Anahtarı",
    "cors": "CORS Ayarları",
    "endpoints": {
        "label": "Uç Noktalar (Endpoints)",
        "lmStudioRestV1": "LM Studio REST API v1"
    },
    "runtimeSettings": "Çalışma Zamanı Ayarları",
    "runtimes": "Çalışma Zamanları",
    "logs": "Loglar / Kayıtlar",
    "clearLogs": "Logları Temizle",
    "exportLogs": "Logları Dışa Aktar"
}